cell_key_perturbation/__init__.py
cell_key_perturbation/bigquery.py
cell_key_perturbation/create_perturbed_table.py
cell_key_perturbation/utils/__init__.py
cell_key_perturbation/utils/generate_record_key.py
cell_key_perturbation/utils/generate_test_data.py
cell_key_perturbation/utils/generate_test_ptable.py
cell_key_perturbation/utils/perturbation_bigquery.py
cell_key_perturbation/utils/validate_inputs_before_perturbation.py
cell_key_perturbation-3.0.0.data/data/__init__.py
cell_key_perturbation-3.0.0.data/data/ptable_10_5_rule.csv
cell_key_perturbation-3.0.0.dist-info/licenses/LICENSE
cell_key_perturbation-3.0.0.dist-info/WHEEL
cell_key_perturbation-3.0.0.dist-info/METADATA
cell_key_perturbation-3.0.0.dist-info/RECORD
