Metadata-Version: 2.4
Name: cell_key_perturbation
Version: 3.0.0
Summary: This package creates frequency tables from microdata, and applies cell key perturbation to alter the final values
Author: Ahmet Aydin
Author-email: Iain Dove <sdc.queries@ons.gov.uk>
Classifier: License :: OSI Approved :: MIT License
License-File: LICENSE
